{
  "@timestamp": "2026-03-31T13:15:29.274Z",
  "processor": {
    "name": "transaction",
    "event": "transaction"
  },
  "trace": {
    "id": "a51f04d889e1fbde50e38eaeace463be"
  },
  "transaction": {
    "id": "f46ded91f56abe4f",
    "name": "pipeline-sqs-handler",
    "type": "messaging",
    "duration": {
      "us": 670000
    },
    "result": "success",
    "sampled": true,
    "span_count": {
      "started": 3,
      "dropped": 0
    },
    "faas": {
      "name": "pipeline-sqs-handler",
      "id": "arn:aws:lambda:eu-south-2:234567890123:function:pipeline-sqs-handler",
      "version": "$LATEST",
      "coldstart": false,
      "execution": "3685fbe8-7ba2-7e5b-2066-ee29c25744ba",
      "trigger": {
        "type": "pubsub"
      }
    }
  },
  "faas": {
    "name": "pipeline-sqs-handler",
    "id": "arn:aws:lambda:eu-south-2:234567890123:function:pipeline-sqs-handler",
    "version": "$LATEST",
    "coldstart": false,
    "execution": "3685fbe8-7ba2-7e5b-2066-ee29c25744ba",
    "trigger": {
      "type": "pubsub"
    }
  },
  "service": {
    "name": "pipeline-sqs-handler",
    "environment": "staging",
    "version": "1.0.0",
    "language": {
      "name": "python"
    },
    "runtime": {
      "name": "python3.12",
      "version": "3.12.3"
    },
    "framework": {
      "name": "AWS Lambda"
    }
  },
  "agent": {
    "name": "otlp",
    "version": "1.0.4"
  },
  "telemetry": {
    "sdk": {
      "name": "opentelemetry",
      "language": "python",
      "version": "1.29.0"
    },
    "distro": {
      "name": "aws-otel",
      "version": "1.0.4"
    }
  },
  "cloud": {
    "provider": "aws",
    "region": "eu-south-2",
    "account": {
      "id": "234567890123",
      "name": "staging-aws"
    },
    "service": {
      "name": "lambda"
    }
  },
  "labels": {
    "s3_notification_prefix": "raw/",
    "sqs_queue": "s3-lake-notifications-staging",
    "landing_bucket": "staging-aws-landing-raw",
    "sqs_message_id": "0f127c84-5d4d-822c-b72e-8654a103ad87",
    "aws.xray.trace_id": "1-6a45e71c-28e7595ce569b1d1b256754c",
    "aws.xray.segment_id": "917cae32ae741aba"
  },
  "event": {
    "outcome": "success"
  },
  "data_stream": {
    "type": "traces",
    "dataset": "apm",
    "namespace": "default"
  }
}
