{
  "@timestamp": "2026-03-31T13:15:29.271Z",
  "cloud": {
    "provider": "aws",
    "region": "ap-northeast-1",
    "account": {
      "id": "164820739518",
      "name": "globex-shared-services"
    },
    "service": {
      "name": "a2i"
    }
  },
  "aws": {
    "dimensions": {
      "FlowDefinitionArn": "arn:aws:sagemaker:ap-northeast-1:164820739518:flow-definition/medical-review",
      "Operation": "StopHumanLoop"
    },
    "a2i": {
      "flow_definition_arn": "arn:aws:sagemaker:ap-northeast-1:164820739518:flow-definition/medical-review",
      "human_loop_name": "loop-981imh7pvzt",
      "human_loop_status": "Stopped",
      "input_content_type": "application/json",
      "condition_threshold": 0.85,
      "human_review_required": true,
      "reviewer_count": 4,
      "task_count": 2,
      "task_completed": 2,
      "confidence_threshold_breach": true
    }
  },
  "log": {
    "level": "warn"
  },
  "event": {
    "action": "StopHumanLoop",
    "outcome": "success",
    "category": ["process"],
    "dataset": "aws.a2i",
    "provider": "sagemaker.amazonaws.com"
  },
  "message": "A2I StopHumanLoop: loop=loop-981imh7pvzt, status=Stopped, confidence=0.77<0.85 REVIEW REQUIRED"
}
