{
  "@timestamp": "2026-03-31T13:15:29.271Z",
  "cloud": {
    "provider": "aws",
    "region": "eu-west-1",
    "account": {
      "id": "738291046572",
      "name": "globex-development"
    },
    "service": {
      "name": "appconfig"
    }
  },
  "aws": {
    "dimensions": {
      "Application": "DataPipeline",
      "Environment": "prod"
    },
    "appconfig": {
      "application_name": "DataPipeline",
      "environment_name": "prod",
      "configuration_profile": "AppSettings",
      "deployment_number": 325,
      "deployment_strategy": "Canary10Percent20Minutes",
      "growth_factor": 33,
      "percentage_complete": 100,
      "state": "COMPLETE"
    }
  },
  "event": {
    "action": "ValidateConfiguration",
    "outcome": "success",
    "category": ["configuration"],
    "dataset": "aws.appconfig",
    "provider": "appconfig.amazonaws.com"
  },
  "message": "AppConfig DataPipeline/prod: AppSettings deployment #325 COMPLETE",
  "log": {
    "level": "info"
  }
}
