{
  "@timestamp": "2026-03-25T12:11:41.550Z",
  "cloud": {
    "provider": "aws",
    "region": "us-east-1",
    "account": {
      "id": "293847561023",
      "name": "globex-staging"
    },
    "service": {
      "name": "aurora"
    }
  },
  "aws": {
    "aurora": {
      "cluster_id": "staging-aurora",
      "instance_id": "staging-aurora-instance-3",
      "engine": "aurora-mysql",
      "engine_version": "8.0.36",
      "replica_lag_seconds": 0.164,
      "db_connections": 341,
      "max_connections": 1000,
      "failover_in_progress": false,
      "metrics": {
        "AuroraBinlogReplicaLag": {
          "avg": 10
        },
        "AuroraGlobalDBReplicatedWriteIO": {
          "sum": 87045939
        },
        "AuroraGlobalDBDataTransferBytes": {
          "sum": 513839324
        },
        "AuroraGlobalDBProgressLag": {
          "avg": 252
        },
        "BacktrackChangeRecordsCreationRate": {
          "avg": 7116
        },
        "BacktrackChangeRecordsStored": {
          "avg": 533376037
        },
        "BacktrackWindowActual": {
          "avg": 65096
        },
        "BacktrackWindowAlert": {
          "avg": 0
        },
        "ServerlessDatabaseCapacity": {
          "avg": 78.973
        },
        "ACUUtilization": {
          "avg": 19.064
        }
      }
    }
  },
  "event": {
    "outcome": "success",
    "category": [
      "database"
    ],
    "dataset": "aws.aurora",
    "provider": "rds.amazonaws.com",
    "duration": 33000000000
  },
  "message": "Cluster endpoint updated",
  "log": {
    "level": "info"
  }
}