{
  "@timestamp": "2026-03-31T10:14:12.846Z",
  "cloud": {
    "provider": "aws",
    "region": "il-central-1",
    "account": {
      "id": "814726593401",
      "name": "globex-production"
    },
    "service": {
      "name": "chimesdkvoice"
    }
  },
  "aws": {
    "dimensions": {
      "VoiceConnectorId": "abcdefghNS1GJ19KU1",
      "Direction": "Inbound"
    },
    "chimesdkvoice": {
      "voice_connector_id": "abcdefghNS1GJ19KU1",
      "call_id": "y8egzm73-w79u-eh1j-jct9-p0hmjmia8hp",
      "direction": "Inbound",
      "call_status": "InProgress",
      "from_number": "+17122421549",
      "to_number": "+15646608888",
      "duration_seconds": 1195,
      "packet_loss_percent": "0.192",
      "mos_score": "4.244",
      "jitter_ms": 20,
      "sip_response_code": 180
    }
  },
  "event": {
    "action": "CallAnswered",
    "outcome": "success",
    "category": [
      "network",
      "session"
    ],
    "dataset": "aws.chimesdkvoice",
    "provider": "chime.amazonaws.com"
  },
  "message": "Chime SDK Voice Inbound call 1195s MOS:4.244 loss:0.192%",
  "log": {
    "level": "info"
  }
}