{
  "@timestamp": "2026-03-26T16:46:26.654Z",
  "cloud": {
    "provider": "aws",
    "region": "eu-west-1",
    "account": {
      "id": "293847561023",
      "name": "globex-staging"
    },
    "service": {
      "name": "codecommit"
    }
  },
  "aws": {
    "codecommit": {
      "repository_name": "infrastructure",
      "repository_arn": "arn:aws:codecommit:eu-west-1:293847561023:infrastructure",
      "event_type": "ReferenceDeleted",
      "reference_name": "feature/new-auth",
      "commit_id": "t2x1oz42egb",
      "author": "bob",
      "files_changed": 46,
      "lines_added": 483,
      "lines_deleted": 71,
      "error_code": "EncryptionKeyUnavailableException"
    }
  },
  "user": {
    "name": "alice"
  },
  "event": {
    "action": "ReferenceDeleted",
    "outcome": "failure",
    "category": [
      "configuration",
      "file"
    ],
    "dataset": "aws.codecommit",
    "provider": "codecommit.amazonaws.com"
  },
  "message": "CodeCommit ReferenceDeleted FAILED on infrastructure: Repository size limit",
  "log": {
    "level": "error"
  },
  "error": {
    "code": "EncryptionKeyUnavailableException",
    "message": "CodeCommit operation failed",
    "type": "vcs"
  }
}