{
  "@timestamp": "2026-03-27T13:21:40.756Z",
  "cloud": {
    "provider": "aws",
    "region": "ap-northeast-1",
    "account": {
      "id": "293847561023",
      "name": "globex-staging"
    },
    "service": {
      "name": "codeartifact"
    }
  },
  "aws": {
    "codeartifact": {
      "domain_name": "corp-packages",
      "repository_name": "nuget-store",
      "package_format": "maven",
      "package_name": "shared-components",
      "package_version": "4.0.3",
      "action": "PublishPackageVersion",
      "download_size_bytes": 23929995
    }
  },
  "event": {
    "action": "PublishPackageVersion",
    "outcome": "success",
    "category": [
      "package",
      "process"
    ],
    "dataset": "aws.codeartifact",
    "provider": "codeartifact.amazonaws.com"
  },
  "message": "CodeArtifact PublishPackageVersion: shared-components@4.0.3 [maven] in corp-packages/nuget-store",
  "log": {
    "level": "info"
  }
}