{
  "@timestamp": "2026-03-26T16:46:26.654Z",
  "cloud": {
    "provider": "aws",
    "region": "ap-southeast-4",
    "account": {
      "id": "738291046572",
      "name": "globex-development"
    },
    "service": {
      "name": "cognito"
    }
  },
  "aws": {
    "dimensions": {
      "UserPool": "ap-southeast-4_8AVTKQF5G",
      "UserPoolClient": "mobile-users-web"
    },
    "cognito": {
      "user_pool_id": "ap-southeast-4_8AVTKQF5G",
      "user_pool_name": "mobile-users",
      "event_type": "UserMigration",
      "username": "user-boigs8v7@example.com",
      "source_ip": "205.248.46.82",
      "metrics": {
        "SignInSuccesses": {
          "sum": 5891
        },
        "SignInAttempts": {
          "sum": 5891
        },
        "TokenRefreshSuccesses": {
          "sum": 42101
        },
        "SignUpSuccesses": {
          "sum": 0
        },
        "FederationSuccesses": {
          "sum": 0
        },
        "CallCount": {
          "sum": 58176
        },
        "ThrottleCount": {
          "sum": 0
        },
        "AccountTakeoverRisk": {
          "sum": 0
        },
        "CompromisedCredentialsRisk": {
          "sum": 0
        }
      }
    }
  },
  "user": {
    "name": "user-boigs8v7@example.com"
  },
  "source": {
    "ip": "229.73.31.32"
  },
  "event": {
    "action": "UserMigration",
    "outcome": "success",
    "category": [
      "authentication"
    ],
    "dataset": "aws.cognito",
    "provider": "cognito-idp.amazonaws.com"
  },
  "message": "Cognito UserMigration success [mobile-users]",
  "log": {
    "level": "info"
  }
}