{
  "@timestamp": "2026-03-17T11:03:53.682Z",
  "cloud": {
    "provider": "aws",
    "region": "us-east-1",
    "account": {
      "id": "814726593401",
      "name": "globex-production"
    },
    "service": {
      "name": "devopsguru"
    }
  },
  "aws": {
    "devopsguru": {
      "insight_id": "0hay1bcs2kp6",
      "insight_type": "PROACTIVE",
      "severity": "MEDIUM",
      "resource_collection": {
        "cloud_formation": {
          "stack_names": [
            "prod-stack"
          ]
        },
        "tags": [
          {
            "key": "environment",
            "value": "production"
          }
        ]
      },
      "anomaly_id": "srbty3j6gal",
      "anomaly_description": "RDS CPU spike correlated with API latency",
      "anomaly_sources": [
        "ecs-workers"
      ],
      "start_time": "2026-03-17T11:03:14.711Z",
      "end_time": "2026-03-17T11:03:53.813Z",
      "status": "CLOSED",
      "recommendation": "Review alarm thresholds",
      "ssm_ops_items": []
    }
  },
  "event": {
    "outcome": "success",
    "category": "process",
    "dataset": "aws.devopsguru",
    "provider": "devops-guru.amazonaws.com"
  },
  "message": "DevOps Guru PROACTIVE insight [MEDIUM]: RDS CPU spike correlated with API latency",
  "log": {
    "level": "info"
  }
}