{
  "@timestamp": "2026-03-16T14:23:43.329Z",
  "cloud": {
    "provider": "aws",
    "region": "eu-west-2",
    "account": {
      "id": "501938274650",
      "name": "globex-security-tooling"
    },
    "service": {
      "name": "emr"
    }
  },
  "aws": {
    "emr": {
      "cluster_id": "j-Y3CG6EUJ0V",
      "cluster_name": "etl-daily-aggregation-cluster",
      "application": "hadoop",
      "release": "emr-6.9.0",
      "instance_group": "TASK",
      "executor_count": 24,
      "job": {
        "name": "etl-daily-aggregation",
        "id": "application_1773671023534_4461"
      },
      "structured_logging": false,
      "metrics": {
        "executor_count": 24,
        "running_step_count": 2,
        "failed_step_count": 0,
        "hdfs_utilization_pct": 37,
        "yarn_memory_used_mb": 65438
      }
    }
  },
  "log": {
    "level": "info"
  },
  "event": {
    "outcome": "success",
    "category": "process",
    "dataset": "aws.emr",
    "provider": "elasticmapreduce.amazonaws.com",
    "duration": 2348000000000
  },
  "message": "Stage 0 (Map) completed in 12.4s"
}