{
  "@timestamp": "2026-03-19T15:13:42.103Z",
  "cloud": {
    "provider": "aws",
    "region": "us-east-1",
    "account": {
      "id": "293847561023",
      "name": "globex-staging"
    },
    "service": {
      "name": "forecast"
    }
  },
  "aws": {
    "dimensions": {
      "DatasetGroup": "web-traffic",
      "Operation": "CreatePredictor"
    },
    "forecast": {
      "dataset_group": "web-traffic",
      "predictor_name": "web-traffic-predictor-v6",
      "action": "CreatePredictor",
      "algorithm": "NPTS",
      "forecast_horizon": 30,
      "weighted_quantile_loss": 0.221,
      "duration_seconds": 4998,
      "status": "ACTIVE"
    }
  },
  "event": {
    "duration": 4998000000000,
    "outcome": "success",
    "category": [
      "process"
    ],
    "dataset": "aws.forecast",
    "provider": "forecast.amazonaws.com"
  },
  "message": "Forecast CreatePredictor: web-traffic, WQL=0.221",
  "log": {
    "level": "info"
  }
}