{
  "@timestamp": "2026-03-17T10:07:40.656Z",
  "cloud": {
    "provider": "aws",
    "region": "eu-west-2",
    "account": {
      "id": "164820739518",
      "name": "globex-shared-services"
    },
    "service": {
      "name": "greengrass"
    }
  },
  "aws": {
    "greengrass": {
      "core_device_name": "factory-edge",
      "component_name": "com.example.inference",
      "component_version": "2.1.5",
      "nucleus_version": "2.12.0",
      "platform": "linux/arm64",
      "deployment_id": "dibqf97m74p",
      "status": "COMPLETED"
    }
  },
  "event": {
    "outcome": "success",
    "category": "process",
    "dataset": "aws.greengrass",
    "provider": "greengrass.amazonaws.com"
  },
  "message": "Nucleus updated to 2.12.0",
  "log": {
    "level": "info"
  }
}