{
  "@timestamp": "2026-03-17T11:03:53.682Z",
  "cloud": {
    "provider": "aws",
    "region": "eu-west-2",
    "account": {
      "id": "164820739518",
      "name": "globex-shared-services"
    },
    "service": {
      "name": "health"
    }
  },
  "aws": {
    "health": {
      "event_arn": "arn:aws:health:eu-west-2::event/ec2/pwk9kbvg/9zw91qxxfoe",
      "event_type_code": "AWS_EC2_MAINTENANCE_SCHEDULED",
      "event_type_category": "accountNotification",
      "service": "EC2",
      "region": "eu-west-2",
      "status_code": "closed",
      "event_scope": "PUBLIC",
      "affected_entities_count": 27,
      "description": "EC2 Connectivity issues in eu-west-2"
    }
  },
  "event": {
    "kind": "alert",
    "outcome": "success",
    "category": "configuration",
    "dataset": "aws.health",
    "provider": "health.amazonaws.com"
  },
  "message": "AWS Health: EC2 event resolved in eu-west-2",
  "log": {
    "level": "info"
  }
}