{
  "@timestamp": "2026-03-30T12:56:00.184Z",
  "cloud": {
    "provider": "aws",
    "region": "af-south-1",
    "account": {
      "id": "293847561023",
      "name": "globex-staging"
    },
    "service": {
      "name": "iotfleetwise"
    }
  },
  "aws": {
    "dimensions": {
      "FleetId": "delivery-vans",
      "CampaignName": "battery-monitoring"
    },
    "iotfleetwise": {
      "fleet_id": "delivery-vans",
      "vehicle_id": "VIN-W7CCL3VZYMH",
      "campaign_name": "battery-monitoring",
      "campaign_status": "RUNNING",
      "signal_name": "Vehicle.OBD.EngineLoad",
      "signal_value": 75.381,
      "collection_scheme": "TIME_BASED",
      "compression": "SNAPPY",
      "data_destination": "S3"
    }
  },
  "event": {
    "action": "CreateFleet",
    "outcome": "success",
    "category": ["iot", "process"],
    "dataset": "aws.iotfleetwise",
    "provider": "iotfleetwise.amazonaws.com"
  },
  "message": "IoT FleetWise CreateFleet: fleet=delivery-vans, vehicle=VIN-W7CCL3VZYMH, campaign=battery-monitoring RUNNING",
  "log": {
    "level": "info"
  }
}
