{
  "@timestamp": "2026-03-16T14:23:43.329Z",
  "cloud": {
    "provider": "aws",
    "region": "us-east-1",
    "account": {
      "id": "501938274650",
      "name": "globex-security-tooling"
    },
    "service": {
      "name": "iotsitewise"
    }
  },
  "aws": {
    "iotsitewise": {
      "asset_id": "lubbmtdbvef",
      "asset_name": "turbine-gen-3",
      "asset_model_id": "t68rjzk349",
      "property_alias": "/company/plant/turbine-gen-3/oee",
      "property_name": "OEE",
      "data_type": "STRING",
      "value": 359.38,
      "quality": "GOOD",
      "timestamp_offset_ms": 890,
      "portal_id": "jb5h65lct6"
    }
  },
  "event": {
    "outcome": "success",
    "category": "host",
    "dataset": "aws.iotsitewise",
    "provider": "iotsitewise.amazonaws.com"
  },
  "message": "IoT SiteWise turbine-gen-3/OEE: 359.38 [GOOD]",
  "log": {
    "level": "info"
  }
}