{
  "@timestamp": "2026-04-01T05:27:12.782Z",
  "cloud": {
    "provider": "aws",
    "region": "eu-south-2",
    "account": {
      "id": "814726593401",
      "name": "globex-production"
    },
    "service": {
      "name": "kendra"
    }
  },
  "aws": {
    "dimensions": {
      "IndexId": "hzxmx042-9bhv-c6f5-va46-ygzcrwcvwro",
      "Operation": "StartDataSourceSyncJob"
    },
    "kendra": {
      "index_id": "hzxmx042-9bhv-c6f5-va46-ygzcrwcvwro",
      "index_name": "company-wiki",
      "result_count": 12,
      "response_time_ms": 62,
      "document_count": 313091,
      "data_source_id": "ds-7ml1fyyjg3",
      "data_source_type": "ServiceNow"
    }
  },
  "log": {
    "level": "info"
  },
  "event": {
    "action": "StartDataSourceSyncJob",
    "outcome": "success",
    "category": [
      "process"
    ],
    "dataset": "aws.kendra",
    "provider": "kendra.amazonaws.com",
    "duration": 62000000
  },
  "message": "Kendra StartDataSourceSyncJob: index=company-wiki"
}