{
  "@timestamp": "2026-03-25T12:11:41.550Z",
  "cloud": {
    "provider": "aws",
    "region": "eu-west-2",
    "account": {
      "id": "738291046572",
      "name": "globex-development"
    },
    "service": {
      "name": "keyspaces"
    }
  },
  "aws": {
    "keyspaces": {
      "keyspace_name": "user_data",
      "table_name": "users",
      "operation": "DELETE",
      "read_capacity_units": 45.58,
      "write_capacity_units": 40.92,
      "rows_returned": 0,
      "duration_ms": 34,
      "cql_version": "3.11.2"
    }
  },
  "event": {
    "duration": 34334000,
    "outcome": "success",
    "category": "database",
    "dataset": "aws.keyspaces",
    "provider": "cassandra.amazonaws.com"
  },
  "message": "Keyspaces DELETE on user_data.users: 34ms",
  "log": {
    "level": "info"
  }
}