{
  "@timestamp": "2026-03-25T12:11:41.550Z",
  "cloud": {
    "provider": "aws",
    "region": "eu-west-2",
    "account": {
      "id": "164820739518",
      "name": "globex-shared-services"
    },
    "service": {
      "name": "lex"
    }
  },
  "aws": {
    "dimensions": {
      "BotName": "customer-service-bot",
      "Operation": "BookAppointment"
    },
    "lex": {
      "bot_id": "H0MJZEU1ZK",
      "bot_name": "customer-service-bot",
      "bot_version": "1",
      "locale_id": "en_GB",
      "session_id": "jmy8vbfncy",
      "input_transcript": "What is my order status",
      "intent_name": "BookAppointment",
      "intent_nlu_confidence_score": 0.902,
      "dialog_state": "Fulfilled",
      "sentiment": "POSITIVE"
    }
  },
  "event": {
    "outcome": "success",
    "category": [
      "process"
    ],
    "dataset": "aws.lex",
    "provider": "lex.amazonaws.com"
  },
  "message": "Lex customer-service-bot: intent=BookAppointment (90%)",
  "log": {
    "level": "info"
  }
}