{
  "@timestamp": "2026-03-31T10:14:12.846Z",
  "cloud": {
    "provider": "aws",
    "region": "eu-central-2",
    "account": {
      "id": "738291046572",
      "name": "globex-development"
    },
    "service": {
      "name": "lookoutvision"
    }
  },
  "aws": {
    "dimensions": {
      "ProjectName": "circuit-board-inspection",
      "ModelVersion": "4.0"
    },
    "lookoutvision": {
      "project_name": "circuit-board-inspection",
      "model_version": "4.0",
      "model_arn": "arn:aws:lookoutvision:eu-central-2:738291046572:model/circuit-board-inspection/4.0",
      "event_type": "DetectAnomalies",
      "image_source": "camera-stream",
      "is_anomalous": false,
      "confidence": 0.882,
      "inference_latency_ms": 292
    }
  },
  "event": {
    "outcome": "success",
    "category": [
      "process"
    ],
    "dataset": "aws.lookoutvision",
    "provider": "lookoutvision.amazonaws.com",
    "duration": 292000000
  },
  "message": "Lookout for Vision [circuit-board-inspection] OK confidence=0.882 292ms",
  "log": {
    "level": "info"
  }
}