{
  "@timestamp": "2026-03-17T13:19:51.676Z",
  "cloud": {
    "provider": "aws",
    "region": "us-east-1",
    "account": {
      "id": "164820739518",
      "name": "globex-shared-services"
    },
    "service": {
      "name": "mediaconvert"
    }
  },
  "aws": {
    "mediaconvert": {
      "job_id": "8276739380-5gwr1p",
      "queue_arn": "arn:aws:mediaconvert:us-east-1:164820739518:queues/premium",
      "job_status": "COMPLETE",
      "output_group_type": "MP4",
      "input_file": "s3://uploads/user-video.mp4",
      "input_duration_minutes": 107.1,
      "video_codec": "H_264",
      "audio_codec": "AC3",
      "width": 1280,
      "height": 2160,
      "bitrate_kbps": 3000,
      "duration_seconds": 530
    }
  },
  "event": {
    "duration": 530000000000,
    "outcome": "success",
    "category": "process",
    "dataset": "aws.mediaconvert",
    "provider": "mediaconvert.amazonaws.com"
  },
  "message": "MediaConvert job 8276739380-5gwr1p COMPLETE: 107.1 min -> MP4",
  "log": {
    "level": "info"
  }
}