{
  "@timestamp": "2026-03-26T17:51:02.372Z",
  "cloud": {
    "provider": "aws",
    "region": "ap-south-1",
    "account": {
      "id": "738291046572",
      "name": "globex-development"
    },
    "service": {
      "name": "medialive"
    }
  },
  "aws": {
    "dimensions": {
      "ChannelId": "LLZ22IHI2OA",
      "Pipeline": "PIPELINE_1"
    },
    "medialive": {
      "channel_id": "LLZ22IHI2OA",
      "channel_name": "concert-stream",
      "channel_state": "IDLE",
      "pipeline": "PIPELINE_1",
      "input_type": "UDP_PUSH",
      "output_type": "DASH",
      "video_bitrate_kbps": 5263,
      "input_loss_frames": 0,
      "encoder_fps": 29.97,
      "metrics": {
        "ActiveAlerts": {
          "sum": 0
        },
        "ChannelInputErrorSeconds": {
          "sum": 0
        },
        "NetworkOut": {
          "avg": 13635920
        },
        "OutputLossSeconds": {
          "sum": 0
        },
        "FillMsec": {
          "sum": 0
        }
      }
    }
  },
  "event": {
    "outcome": "success",
    "category": [
      "process"
    ],
    "dataset": "aws.medialive",
    "provider": "medialive.amazonaws.com",
    "duration": 5829000000
  },
  "message": "Input switch to backup completed",
  "log": {
    "level": "info"
  }
}