{
  "@timestamp": "2026-03-26T17:22:32.197Z",
  "cloud": {
    "provider": "aws",
    "region": "us-west-2",
    "account": {
      "id": "814726593401",
      "name": "globex-production"
    },
    "service": {
      "name": "migrationhub"
    }
  },
  "aws": {
    "migrationhub": {
      "application_id": "app-ubddb10tll7",
      "application_name": "web-tier-migration",
      "server_id": "d-server-4SDS9UY082B",
      "server_name": "server-b53u4biw",
      "migration_status": "MIGRATION_COMPLETE",
      "migration_tool": "CloudEndure",
      "progress_update_stream": "MGN-stream",
      "task": {
        "status": "IN_PROGRESS",
        "progress_percent": 81,
        "total_objects": 66,
        "replicated_objects": 366
      }
    }
  },
  "event": {
    "outcome": "success",
    "category": [
      "process",
      "configuration"
    ],
    "dataset": "aws.migrationhub",
    "provider": "mgh.amazonaws.com",
    "duration": 5619000000000
  },
  "message": "Migration Hub web-tier-migration [CloudEndure]: MIGRATION_COMPLETE — server-b53u4biw",
  "log": {
    "level": "info"
  }
}