{
  "@timestamp": "2026-03-16T15:20:27.243Z",
  "cloud": {
    "provider": "aws",
    "region": "us-east-1",
    "account": {
      "id": "293847561023",
      "name": "globex-staging"
    },
    "service": {
      "name": "quicksight"
    }
  },
  "aws": {
    "quicksight": {
      "dashboard_id": "rwl3wtq7w7a",
      "dashboard_name": "ops-metrics",
      "action": "RefreshDataSet",
      "user_name": "carol@corp.com",
      "data_source_type": "RDS",
      "query_duration_ms": 262,
      "rows_returned": 13774
    }
  },
  "user": {
    "name": "carol@corp.com"
  },
  "event": {
    "duration": 262000000,
    "outcome": "success",
    "category": "database",
    "dataset": "aws.quicksight",
    "provider": "quicksight.amazonaws.com"
  },
  "message": "QuickSight RefreshDataSet: ops-metrics loaded in 262ms for carol@corp.com",
  "log": {
    "level": "info"
  }
}