{
  "@timestamp": "2026-03-16T16:55:00.054Z",
  "cloud": {
    "provider": "aws",
    "region": "eu-west-2",
    "account": {
      "id": "738291046572",
      "name": "globex-development"
    },
    "service": {
      "name": "ram"
    }
  },
  "aws": {
    "ram": {
      "resource_share_arn": "arn:aws:ram:eu-west-2:738291046572:resource-share/ytuarvwixbp",
      "resource_share_name": "resolver-rules-share",
      "resource_type": "license-manager:LicenseConfiguration",
      "action": "CreateResourceShare",
      "principal": "738291046572",
      "allow_external_principals": true,
      "status": "PENDING"
    }
  },
  "event": {
    "action": "CreateResourceShare",
    "outcome": "success",
    "category": "iam",
    "dataset": "aws.ram",
    "provider": "ram.amazonaws.com"
  },
  "message": "RAM CreateResourceShare: license-manager:LicenseConfiguration shared with account 738291046572",
  "log": {
    "level": "info"
  }
}