{
  "@timestamp": "2026-03-16T14:23:43.329Z",
  "cloud": {
    "provider": "aws",
    "region": "us-east-1",
    "account": {
      "id": "164820739518",
      "name": "globex-shared-services"
    },
    "service": {
      "name": "ram"
    }
  },
  "aws": {
    "ram": {
      "resource_share_arn": "arn:aws:ram:us-east-1:164820739518:resource-share/w58qwto5zwm",
      "resource_share_name": "shared-subnets",
      "resource_type": "ram:ResourceShare",
      "action": "CreateResourceShare",
      "principal": "164820739518",
      "allow_external_principals": true,
      "status": "PENDING"
    }
  },
  "event": {
    "action": "CreateResourceShare",
    "outcome": "success",
    "category": "iam",
    "dataset": "aws.ram",
    "provider": "ram.amazonaws.com"
  },
  "message": "RAM CreateResourceShare: ram:ResourceShare shared with account 164820739518",
  "log": {
    "level": "info"
  }
}