{
  "@timestamp": "2026-03-25T11:55:50.848Z",
  "cloud": {
    "provider": "aws",
    "region": "eu-west-2",
    "account": {
      "id": "738291046572",
      "name": "globex-development"
    },
    "service": {
      "name": "securityhub"
    }
  },
  "aws": {
    "dimensions": {
      "ComplianceStandard": "pci-dss",
      "ControlId": "Lambda.1"
    },
    "securityhub_findings": {
      "id": "X0DVQN4B-K86R-HD6A-T22B-IMNUD4YMU3G",
      "aws_account_id": "738291046572",
      "region": "eu-west-2",
      "description": "Control passed.",
      "created_at": "2026-03-24T16:06:44.961Z",
      "first_observed_at": "2026-03-24T16:06:44.961Z",
      "last_observed_at": "2026-03-25T11:55:50.848Z",
      "generator": {
        "id": "Lambda.1"
      },
      "types": [
        "Software and Configuration Checks/Vulnerabilities/CVE"
      ],
      "compliance": {
        "security_control_id": "Lambda.1",
        "status": "PASSED"
      },
      "severity": {
        "label": "INFORMATIONAL",
        "normalized": 0
      },
      "workflow": {
        "status": "SUPPRESSED"
      },
      "record_state": "ARCHIVED",
      "product": {
        "arn": "arn:aws:securityhub:eu-west-2::product/aws/securityhub",
        "name": "Security Hub"
      },
      "criticality": 4,
      "confidence": 85
    }
  },
  "rule": {
    "id": "Lambda.1",
    "name": "Lambda.1 — S3 bucket publicly accessible"
  },
  "event": {
    "kind": "alert",
    "severity": 4,
    "outcome": "success",
    "category": [
      "compliance"
    ],
    "type": [
      "info"
    ],
    "dataset": "aws.securityhub_findings",
    "provider": "securityhub.amazonaws.com"
  },
  "message": "Security Hub: control passed",
  "log": {
    "level": "info"
  }
}