{
  "@timestamp": "2026-03-30T12:56:00.184Z",
  "cloud": {
    "provider": "aws",
    "region": "eu-west-1",
    "account": {
      "id": "293847561023",
      "name": "globex-staging"
    }
  },
  "aws": {
    "amazonmq": {
      "metrics": {
        "EnqueueCount": {
          "avg": 93935,
          "sum": 93935,
          "count": 1
        },
        "DequeueCount": {
          "avg": 96017,
          "sum": 96017,
          "count": 1
        },
        "QueueSize": {
          "avg": 3935,
          "sum": 3935,
          "count": 1
        },
        "ExpiredCount": {
          "avg": 0,
          "sum": 0,
          "count": 1
        },
        "DispatchCount": {
          "avg": 22895,
          "sum": 22895,
          "count": 1
        },
        "ConsumerCount": {
          "avg": 29,
          "sum": 29,
          "count": 1
        },
        "ProducerCount": {
          "avg": 10,
          "sum": 10,
          "count": 1
        },
        "TotalConsumerCount": {
          "avg": 133,
          "sum": 133,
          "count": 1
        },
        "TotalProducerCount": {
          "avg": 88,
          "sum": 88,
          "count": 1
        },
        "HeapUsage": {
          "avg": 38.11,
          "sum": 38.11,
          "count": 1
        },
        "CPUCreditBalance": {
          "avg": 133.88,
          "sum": 133.88,
          "count": 1
        },
        "NetworkIn": {
          "avg": 2496449534,
          "sum": 2496449534,
          "count": 1
        },
        "NetworkOut": {
          "avg": 3353409536,
          "sum": 3353409536,
          "count": 1
        }
      },
      "dimensions": {
        "Broker": "b-1a2b3c4d-2",
        "Queue": "dlq"
      }
    }
  },
  "metricset": {
    "name": "amazonmq",
    "period": 60000
  },
  "data_stream": {
    "type": "metrics",
    "dataset": "aws.amazonmq",
    "namespace": "default"
  },
  "event": {
    "dataset": "aws.amazonmq",
    "module": "aws"
  }
}