{
  "@timestamp": "2026-04-01T05:27:12.782Z",
  "cloud": {
    "provider": "aws",
    "region": "us-east-2",
    "account": {
      "id": "293847561023",
      "name": "globex-staging"
    }
  },
  "aws": {
    "apigateway": {
      "metrics": {
        "Count": {
          "avg": 60126,
          "sum": 60126,
          "count": 1
        },
        "4XXError": {
          "avg": 2021,
          "sum": 2021,
          "count": 1
        },
        "5XXError": {
          "avg": 276,
          "sum": 276,
          "count": 1
        },
        "Latency": {
          "avg": 107.89,
          "sum": 107.89,
          "count": 1,
          "max": 2394.35,
          "min": 11.12
        },
        "IntegrationLatency": {
          "avg": 86.96,
          "sum": 86.96,
          "count": 1
        },
        "CacheHitCount": {
          "avg": 8749,
          "sum": 8749,
          "count": 1
        },
        "CacheMissCount": {
          "avg": 8886,
          "sum": 8886,
          "count": 1
        }
      },
      "dimensions": {
        "ApiName": "products-api",
        "Stage": "prod"
      }
    }
  },
  "metricset": {
    "name": "apigateway",
    "period": 60000
  },
  "data_stream": {
    "type": "metrics",
    "dataset": "aws.apigateway_metrics",
    "namespace": "default"
  },
  "event": {
    "dataset": "aws.apigateway_metrics",
    "module": "aws"
  }
}