{
  "@timestamp": "2026-03-30T12:56:00.184Z",
  "cloud": {
    "provider": "aws",
    "region": "ca-central-1",
    "account": {
      "id": "501938274650",
      "name": "globex-security-tooling"
    }
  },
  "aws": {
    "aurora": {
      "metrics": {
        "CPUUtilization": {
          "avg": 33.6,
          "sum": 33.6,
          "count": 1
        },
        "DatabaseConnections": {
          "avg": 430,
          "sum": 430,
          "count": 1
        },
        "FreeStorageSpace": {
          "avg": 106234039941.87,
          "sum": 106234039941.87,
          "count": 1
        },
        "FreeableMemory": {
          "avg": 2177006806.2,
          "sum": 2177006806.2,
          "count": 1
        },
        "ReadLatency": {
          "avg": 0,
          "sum": 0,
          "count": 1
        },
        "WriteLatency": {
          "avg": 0,
          "sum": 0,
          "count": 1
        },
        "ReadIOPS": {
          "avg": 3066,
          "sum": 3066,
          "count": 1
        },
        "WriteIOPS": {
          "avg": 171,
          "sum": 171,
          "count": 1
        },
        "ReadThroughput": {
          "avg": 113728860,
          "sum": 113728860,
          "count": 1
        },
        "WriteThroughput": {
          "avg": 299364667,
          "sum": 299364667,
          "count": 1
        },
        "NetworkReceiveThroughput": {
          "avg": 45969458,
          "sum": 45969458,
          "count": 1
        },
        "NetworkTransmitThroughput": {
          "avg": 58834062,
          "sum": 58834062,
          "count": 1
        },
        "DiskQueueDepth": {
          "avg": 0.29,
          "sum": 0.29,
          "count": 1
        },
        "ReplicaLag": {
          "avg": 214.96,
          "sum": 214.96,
          "count": 1
        },
        "BinLogDiskUsage": {
          "avg": 1848168846,
          "sum": 1848168846,
          "count": 1
        }
      },
      "dimensions": {
        "DBInstanceIdentifier": "aurora-global-cluster",
        "DBClusterIdentifier": "aurora-global-cluster"
      }
    }
  },
  "metricset": {
    "name": "aurora",
    "period": 60000
  },
  "data_stream": {
    "type": "metrics",
    "dataset": "aws.rds",
    "namespace": "default"
  },
  "event": {
    "dataset": "aws.rds",
    "module": "aws"
  }
}