{
  "@timestamp": "2026-03-16T14:23:43.329Z",
  "cloud": {
    "provider": "aws",
    "region": "us-east-1",
    "account": {
      "id": "164820739518",
      "name": "globex-shared-services"
    },
    "service": {
      "name": "cloudfront"
    }
  },
  "aws": {
    "dimensions": {
      "DistributionId": "EABAVKIE5LXU",
      "Region": "Global"
    },
    "cloudfront_logs": {
      "x_edge_location": "SFO",
      "sc_bytes": 378504,
      "c_ip": "8.31.237.29",
      "cs_method": "GET",
      "cs_uri_stem": "/assets/app.js",
      "sc_status": "200",
      "x_edge_request_id": "ECNX10FSH6S",
      "time_taken": "0.224",
      "x_edge_result_type": "Miss",
      "x_edge_response_result_type": "Hit"
    },
    "cloudfront": {
      "distribution_id": "EABAVKIE5LXU",
      "edge_location": "SFO",
      "result_type": "RefreshHit",
      "edge_request_id": "ECNX10FSH6S",
      "time_to_first_byte": 0.224,
      "metrics": {
        "Requests": {
          "sum": 16405
        },
        "BytesDownloaded": {
          "sum": 1944861691
        },
        "BytesUploaded": {
          "sum": 616987
        },
        "4xxErrorRate": {
          "avg": 0.395
        },
        "5xxErrorRate": {
          "avg": 0
        },
        "TotalErrorRate": {
          "avg": 0.586
        },
        "CacheHitRate": {
          "avg": 68.65
        },
        "OriginLatency": {
          "avg": 67
        }
      }
    }
  },
  "http": {
    "request": {
      "method": "GET",
      "bytes": 641
    },
    "response": {
      "status_code": 200,
      "bytes": 378504
    }
  },
  "url": {
    "path": "/assets/app.js",
    "domain": "dbx0kuob5h4.cloudfront.net"
  },
  "client": {
    "ip": "8.31.237.29"
  },
  "event": {
    "outcome": "success",
    "category": "web",
    "dataset": "aws.cloudfront_logs",
    "provider": "cloudfront.amazonaws.com",
    "duration": 224000000
  },
  "message": "GET /assets/app.js 200 [SFO]",
  "log": {
    "level": "info"
  },
  "data_stream": {
    "type": "metrics",
    "dataset": "aws.cloudfront_logs",
    "namespace": "default"
  },
  "metricset": {
    "name": "cloudwatch",
    "period": 300000
  }
}