{
  "@timestamp": "2026-03-17T10:07:40.656Z",
  "cloud": {
    "provider": "aws",
    "region": "eu-west-2",
    "availability_zone": "eu-west-2b",
    "account": {
      "id": "501938274650",
      "name": "globex-security-tooling"
    },
    "service": {
      "name": "ebs"
    }
  },
  "aws": {
    "dimensions": {
      "VolumeId": "vol-yxfqy0vbnho",
      "VolumeType": "sc1"
    },
    "ebs": {
      "volume_id": "vol-yxfqy0vbnho",
      "volume_type": "sc1",
      "size_gb": 50,
      "alarm_name": "ebs-volumequeuelength-vol-yxfqy0vbnho",
      "alarm_state": "OK",
      "metric_name": "VolumeQueueLength",
      "threshold": 72,
      "current_value": 2,
      "event_type": "alarm",
      "metrics": {
        "VolumeReadOps": {
          "sum": 2031
        },
        "VolumeWriteOps": {
          "sum": 497
        },
        "VolumeReadBytes": {
          "sum": 64489480
        },
        "VolumeWriteBytes": {
          "sum": 520175547
        },
        "VolumeTotalReadTime": {
          "sum": 8.436
        },
        "VolumeTotalWriteTime": {
          "sum": 1.862
        },
        "VolumeIdleTime": {
          "sum": 55.853
        },
        "VolumeQueueLength": {
          "avg": 1
        },
        "VolumeThroughputPercentage": {
          "avg": 38.556
        },
        "VolumeConsumedReadWriteOps": {
          "sum": 916
        },
        "BurstBalance": {
          "avg": 86
        }
      }
    }
  },
  "event": {
    "outcome": "success",
    "category": "host",
    "dataset": "aws.ebs",
    "provider": "ec2.amazonaws.com"
  },
  "message": "EBS CloudWatch alarm OK: VolumeQueueLength on vol-yxfqy0vbnho within normal range",
  "log": {
    "level": "info"
  },
  "data_stream": {
    "type": "metrics",
    "dataset": "aws.ebs",
    "namespace": "default"
  },
  "metricset": {
    "name": "cloudwatch",
    "period": 300000
  }
}