{
  "@timestamp": "2026-03-31T13:15:29.271Z",
  "cloud": {
    "provider": "aws",
    "region": "eu-central-2",
    "account": {
      "id": "501938274650",
      "name": "globex-security-tooling"
    }
  },
  "aws": {
    "emr": {
      "metrics": {
        "CoreNodesRunning": {
          "avg": 25,
          "sum": 25,
          "count": 1
        },
        "CoreNodesPending": {
          "avg": 0,
          "sum": 0,
          "count": 1
        },
        "TaskNodesRunning": {
          "avg": 23,
          "sum": 23,
          "count": 1
        },
        "TaskNodesPending": {
          "avg": 0,
          "sum": 0,
          "count": 1
        },
        "HDFSUtilization": {
          "avg": 62.49,
          "sum": 62.49,
          "count": 1
        },
        "HDFSBytesRead": {
          "avg": 1451842664,
          "sum": 1451842664,
          "count": 1
        },
        "HDFSBytesWritten": {
          "avg": 38410968132,
          "sum": 38410968132,
          "count": 1
        },
        "ContainerAllocated": {
          "avg": 301,
          "sum": 301,
          "count": 1
        },
        "ContainerReserved": {
          "avg": 3,
          "sum": 3,
          "count": 1
        },
        "ContainerPending": {
          "avg": 45,
          "sum": 45,
          "count": 1
        },
        "MRActiveNodes": {
          "avg": 48,
          "sum": 48,
          "count": 1
        },
        "YARNMemoryAvailablePercentage": {
          "avg": 38.38,
          "sum": 38.38,
          "count": 1
        }
      },
      "dimensions": {
        "JobFlowId": "j-ABCDEF123456",
        "JobFlowName": "spark-etl-prod"
      }
    }
  },
  "metricset": {
    "name": "emr",
    "period": 60000
  },
  "data_stream": {
    "type": "metrics",
    "dataset": "aws.emr_metrics",
    "namespace": "default"
  },
  "event": {
    "dataset": "aws.emr_metrics",
    "module": "aws"
  }
}
