{
  "@timestamp": "2026-03-27T13:21:40.756Z",
  "cloud": {
    "provider": "aws",
    "region": "us-west-2",
    "account": {
      "id": "164820739518",
      "name": "globex-shared-services"
    }
  },
  "aws": {
    "guardduty": {
      "metrics": {
        "FindingsCount": {
          "avg": 98,
          "sum": 98,
          "count": 1
        },
        "HighSeverityFindingsCount": {
          "avg": 0,
          "sum": 0,
          "count": 1
        },
        "MediumSeverityFindingsCount": {
          "avg": 50,
          "sum": 50,
          "count": 1
        },
        "LowSeverityFindingsCount": {
          "avg": 14,
          "sum": 14,
          "count": 1
        },
        "ArchivedFindingsCount": {
          "avg": 174,
          "sum": 174,
          "count": 1
        }
      },
      "dimensions": {
        "DetectorId": "abc123def456ghi789jkl012"
      }
    }
  },
  "metricset": {
    "name": "guardduty",
    "period": 60000
  },
  "data_stream": {
    "type": "metrics",
    "dataset": "aws.guardduty",
    "namespace": "default"
  },
  "event": {
    "dataset": "aws.guardduty",
    "module": "aws"
  }
}