{
  "@timestamp": "2026-03-26T16:46:26.654Z",
  "cloud": {
    "provider": "aws",
    "region": "eu-central-1",
    "account": {
      "id": "501938274650",
      "name": "globex-security-tooling"
    }
  },
  "aws": {
    "kms": {
      "metrics": {
        "Encrypt": {
          "avg": 9009,
          "sum": 9009,
          "count": 1
        },
        "Decrypt": {
          "avg": 23264,
          "sum": 23264,
          "count": 1
        },
        "GenerateDataKey": {
          "avg": 3683,
          "sum": 3683,
          "count": 1
        },
        "Sign": {
          "avg": 1319,
          "sum": 1319,
          "count": 1
        },
        "Verify": {
          "avg": 21,
          "sum": 21,
          "count": 1
        },
        "KeyRotation": {
          "avg": 0,
          "sum": 0,
          "count": 1
        }
      },
      "dimensions": {
        "KeyId": "mrk-aabbccddeeff0011"
      }
    }
  },
  "metricset": {
    "name": "kms",
    "period": 60000
  },
  "data_stream": {
    "type": "metrics",
    "dataset": "aws.kms",
    "namespace": "default"
  },
  "event": {
    "dataset": "aws.kms",
    "module": "aws"
  }
}