{
  "@timestamp": "2026-03-30T12:56:00.184Z",
  "cloud": {
    "provider": "aws",
    "region": "eu-west-1",
    "account": {
      "id": "293847561023",
      "name": "globex-staging"
    }
  },
  "aws": {
    "opensearch": {
      "metrics": {
        "CPUUtilization": {
          "avg": 35.87,
          "sum": 35.87,
          "count": 1
        },
        "JVMMemoryPressure": {
          "avg": 90.7,
          "sum": 90.7,
          "count": 1
        },
        "FreeStorageSpace": {
          "avg": 28459.41,
          "sum": 28459.41,
          "count": 1
        },
        "IndexingRate": {
          "avg": 730.76,
          "sum": 730.76,
          "count": 1
        },
        "SearchRate": {
          "avg": 295.91,
          "sum": 295.91,
          "count": 1
        },
        "IndexingLatency": {
          "avg": 10.51,
          "sum": 10.51,
          "count": 1
        },
        "SearchLatency": {
          "avg": 8.59,
          "sum": 8.59,
          "count": 1
        },
        "ClusterStatus_green": {
          "avg": 1,
          "sum": 1,
          "count": 1
        },
        "ClusterStatus_yellow": {
          "avg": 0,
          "sum": 0,
          "count": 1
        },
        "ClusterStatus_red": {
          "avg": 1,
          "sum": 1,
          "count": 1
        },
        "Nodes": {
          "avg": 14,
          "sum": 14,
          "count": 1
        },
        "AutomatedSnapshotFailure": {
          "avg": 0,
          "sum": 0,
          "count": 1
        },
        "ClusterIndexWritesBlocked": {
          "avg": 0,
          "sum": 0,
          "count": 1
        }
      },
      "dimensions": {
        "DomainName": "analytics-os",
        "ClientId": "293847561023"
      }
    }
  },
  "metricset": {
    "name": "opensearch",
    "period": 60000
  },
  "data_stream": {
    "type": "metrics",
    "dataset": "aws.opensearch",
    "namespace": "default"
  },
  "event": {
    "dataset": "aws.opensearch",
    "module": "aws"
  }
}
