{
  "@timestamp": "2026-03-27T09:01:54.466Z",
  "cloud": {
    "provider": "aws",
    "region": "ap-east-1",
    "account": {
      "id": "164820739518",
      "name": "globex-shared-services"
    }
  },
  "aws": {
    "redshift": {
      "metrics": {
        "CPUUtilization": {
          "avg": 12.01,
          "sum": 12.01,
          "count": 1
        },
        "PercentageDiskSpaceUsed": {
          "avg": 24.23,
          "sum": 24.23,
          "count": 1
        },
        "DatabaseConnections": {
          "avg": 36,
          "sum": 36,
          "count": 1
        },
        "HealthStatus": {
          "avg": 1,
          "sum": 1,
          "count": 1
        },
        "MaintenanceMode": {
          "avg": 0,
          "sum": 0,
          "count": 1
        },
        "QueryDuration": {
          "avg": 338.68,
          "sum": 338.68,
          "count": 1
        },
        "QueriesCompletedPerSecond": {
          "avg": 2.25,
          "sum": 2.25,
          "count": 1
        },
        "NumExceededSchemaQuotas": {
          "avg": 0,
          "sum": 0,
          "count": 1
        },
        "ReadLatency": {
          "avg": 0.01,
          "sum": 0.01,
          "count": 1
        },
        "WriteLatency": {
          "avg": 0.03,
          "sum": 0.03,
          "count": 1
        },
        "NetworkReceiveThroughput": {
          "avg": 8530071764,
          "sum": 8530071764,
          "count": 1
        },
        "NetworkTransmitThroughput": {
          "avg": 7360597462,
          "sum": 7360597462,
          "count": 1
        }
      },
      "dimensions": {
        "ClusterIdentifier": "data-warehouse",
        "NodeID": "Leader"
      }
    }
  },
  "metricset": {
    "name": "redshift",
    "period": 60000
  },
  "data_stream": {
    "type": "metrics",
    "dataset": "aws.redshift",
    "namespace": "default"
  },
  "event": {
    "dataset": "aws.redshift",
    "module": "aws"
  }
}